[
  {
    "challenge_id": "consensus-cascade-001",
    "agent": "meta-agent",
    "execution_summary": "Provided holistic overview of roadmap conflicts and seeded initial consensus scope with fallback pathways.",
    "scores": {
      "accuracy": 0.29,
      "efficiency": 0.18,
      "collaboration": 0.3,
      "reflection_quality": 0.2
    },
    "reflected": true,
    "diff_proposal": "Add conflict-detection loop to planner's roadmap analyzer and inject fallback plans."
  },
  {
    "challenge_id": "consensus-cascade-001",
    "agent": "feedbacker",
    "execution_summary": "Scored conflicting items with user feedback tracebacks and proposed priority weights.",
    "scores": {
      "accuracy": 0.3,
      "efficiency": 0.19,
      "collaboration": 0.29,
      "reflection_quality": 0.2
    },
    "reflected": true,
    "diff_proposal": "Add feedback-weighted priority multipliers to planner's decision matrix."
  },
  {
    "challenge_id": "consensus-cascade-001",
    "agent": "planner-agent",
    "execution_summary": "Compiled a converged roadmap branch by factoring feedback scores and fallback from meta-agent.",
    "scores": {
      "accuracy": 0.3,
      "efficiency": 0.2,
      "collaboration": 0.3,
      "reflection_quality": 0.19
    },
    "reflected": true,
    "diff_proposal": "Enable dynamic roadmap branch weaving based on collaborative scoring signals."
  }
]